kbfs_upload/__init__.py
kbfs_upload/__main__.py
kbfs_upload/config.py
kbfs_upload/server.py
kbfs_upload/utils.py
kbfs_upload-0.1.1.dist-info/entry_points.txt
kbfs_upload-0.1.1.dist-info/LICENSE
kbfs_upload-0.1.1.dist-info/WHEEL
kbfs_upload-0.1.1.dist-info/METADATA
kbfs_upload-0.1.1.dist-info/RECORD
