Metadata-Version: 2.1
Name: kbfs-upload
Version: 0.1.1
Summary: An API for uploading files/notes to a KBFS folder
Home-page: https://github.com/da-code-a/KBFS-Upload-API
License: MIT
Keywords: keybase,upload,docker,api
Author: Dakota Brown
Author-email: dakota.kae.brown@gmail.com
Requires-Python: >=3.6.2,<4.0.0
Classifier: License :: OSI Approved :: MIT License
Classifier: Programming Language :: Python :: 3
Classifier: Programming Language :: Python :: 3.7
Classifier: Programming Language :: Python :: 3.8
Classifier: Programming Language :: Python :: 3.9
Requires-Dist: Flask (>=2.0.1,<3.0.0)
Requires-Dist: pykeybase (>=0.5.0,<0.6.0)
Requires-Dist: python-dotenv (>=0.19.0,<0.20.0)
Project-URL: Repository, https://github.com/da-code-a/KBFS-Upload-API
